Metadata-Version: 2.1
Name: clone-gh
Version: 0.1
Summary: Clone all starred Github repositories for a given username and programming language
Home-page: https://github.com/gusanmaz/clone_gh
Author: Güvenç Usanmaz
Author-email: gusanmaz@gmail.com
License: MIT
Project-URL: Bug Reports, https://github.com/gusanmaz/clone_gh/issues
Project-URL: Source, https://github.com/gusanmaz/clone_gh
Keywords: github,clone,starred,repositories
Platform: any
Classifier: Programming Language :: Python :: 3
Classifier: License :: OSI Approved :: MIT License
Classifier: Operating System :: OS Independent
Requires-Python: >=3.6
License-File: LICENSE
